pyfutebol
