Metadata-Version: 1.0
Name: pyfutebol
Version: 2.2.1
Summary: Crawler para resultados de futebol
Home-page: https://github.com/vinigracindo/pyfutebol/
Author: Vinnicyus Gracindo
Author-email: vini.gracindo@gmail.com
License: MIT
Platform: UNKNOWN
